zops/__init__.py
zops/aws/__init__.py
zops/aws/autoscaling.py
zops/aws/cli.py
zops/aws/cli_commands.py
zops/aws/cli_config.py
zops/aws/cluster.py
zops/aws/config.yml
zops/aws/image.py
zops/aws/instance.py
zops/aws/utils.py
zops/aws/utils_click.py
zops/aws/utils_shell.py
zops.aws-1.0.0.dist-info/METADATA
zops.aws-1.0.0.dist-info/WHEEL
zops.aws-1.0.0.dist-info/entry_points.txt
zops.aws-1.0.0.dist-info/top_level.txt
zops.aws-1.0.0.dist-info/RECORD
